outcome/utils/__init__.py
outcome/utils/bin/otc_utils.py
outcome/utils/cache.py
outcome/utils/config.py
outcome/utils/env.py
outcome/utils/feature_set.py
outcome/utils/jinja2/__init__.py
outcome/utils/jinja2/extend.py
outcome/utils/jinja2/regex_replace.py
outcome/utils/loader.py
outcome/utils/meta.py
outcome/utils/pre_condition.py
outcome/utils/provider_state.py
outcome/utils/py.typed
outcome/utils/pyproject.py
outcome/utils/reraise.py
outcome/utils/semver.py
outcome/utils/transactions.py
outcome/utils/transformer_dict.py
outcome_utils-5.1.0.dist-info/entry_points.txt
outcome_utils-5.1.0.dist-info/WHEEL
outcome_utils-5.1.0.dist-info/METADATA
outcome_utils-5.1.0.dist-info/RECORD
