Metadata-Version: 2.1
Name: outcome-utils
Version: 5.1.0
Summary: A collection of python utils.
Home-page: https://github.com/outcome-co/utils-py
License: ISC
Author: Douglas Willcocks
Author-email: douglas@outcome.co
Requires-Python: >=3.8.6,<4.0.0
Classifier: License :: OSI Approved
Classifier: Programming Language :: Python :: 3
Classifier: Programming Language :: Python :: 3.9
Requires-Dist: asgiref (>=3.2.10,<4.0.0)
Requires-Dist: cachetools (>=4.1.1,<5.0.0)
Requires-Dist: colored (>=1.4.2,<2.0.0)
Requires-Dist: dogpile.cache (>=1.0.2,<2.0.0)
Requires-Dist: jinja2 (>=2.11.2,<3.0.0)
Requires-Dist: makefun (>=1.9.3,<2.0.0)
Requires-Dist: pydantic (>=1.7.3,<2.0.0)
Requires-Dist: python-dotenv (>=0.15,<0.18)
Requires-Dist: requests (>=2.24.0,<3.0.0)
Requires-Dist: rich (>=6.2,<10.0)
Requires-Dist: semver (>=2.10.2,<3.0.0)
Requires-Dist: toml (>=0.10.1,<0.11.0)
Project-URL: Documentation, https://github.com/outcome-co/utils-py#README
Project-URL: Repository, https://github.com/outcome-co/utils-py
